aea_ledger_solana/__init__.py
aea_ledger_solana/account.py
aea_ledger_solana/constants.py
aea_ledger_solana/crypto.py
aea_ledger_solana/faucet.py
aea_ledger_solana/helper.py
aea_ledger_solana/py.typed
aea_ledger_solana/solana.py
aea_ledger_solana/solana_api.py
aea_ledger_solana/transaction.py
aea_ledger_solana/transaction_instruction.py
aea_ledger_solana/utils.py
open_aea_ledger_solana-2.0.8.dist-info/licenses/LICENSE
open_aea_ledger_solana-2.0.8.dist-info/METADATA
open_aea_ledger_solana-2.0.8.dist-info/WHEEL
open_aea_ledger_solana-2.0.8.dist-info/entry_points.txt
open_aea_ledger_solana-2.0.8.dist-info/top_level.txt
open_aea_ledger_solana-2.0.8.dist-info/RECORD
